<?xml version="1.0" encoding="utf-8"?>
<doctrine-mapping xmlns="http://doctrine-project.org/schemas/orm/doctrine-mapping" xmlns:xsi="http://www.w3.org/2001/XMLSchema-instance" xsi:schemaLocation="http://doctrine-project.org/schemas/orm/doctrine-mapping http://doctrine-project.org/schemas/orm/doctrine-mapping.xsd">
  <entity name="CiudadTigre\AnuncianteBundle\Entity\Anunciante" table="anunciante">
    <unique-constraints>
      <unique-constraint name="nombre_UNIQUE" columns="nombre"/>
      <unique-constraint name="rif_UNIQUE" columns="rif"/>
      <unique-constraint name="email_UNIQUE" columns="email"/>
    </unique-constraints>
    <id name="id" type="integer" column="id">
      <generator strategy="IDENTITY"/>
    </id>
    <field name="nombre" type="string" column="nombre" length="250" nullable="false"/>
    <field name="rif" type="string" column="rif" length="10" nullable="false"/>
    <field name="descripcion" type="text" column="descripcion" nullable="true"/>
    <field name="email" type="string" column="email" length="100" nullable="false"/>
    <field name="telefono" type="string" column="telefono" length="11" nullable="true"/>
  </entity>
</doctrine-mapping>
